africanjokes/__init__.py
africanjokes/cli.py
africanjokes/jokes.txt
africanjokes-1.0.1.dist-info/licenses/LICENSE
africanjokes-1.0.1.dist-info/METADATA
africanjokes-1.0.1.dist-info/WHEEL
africanjokes-1.0.1.dist-info/entry_points.txt
africanjokes-1.0.1.dist-info/top_level.txt
africanjokes-1.0.1.dist-info/RECORD
