Metadata-Version: 2.4
Name: africanjokes
Version: 1.0.1
Summary: A library for African jokes
Home-page: https://github.com/daddysboy21/africanjokes
Author: Morris D. Toclo
Author-email: "Morris D. Toclo" <morristoclo@gmail.com>
Maintainer-email: "Morris D. Toclo" <morristoclo@gmail.com>
License: MIT License
Project-URL: Homepage, https://github.com/daddysboy21/africanjokes
Project-URL: Author, https://github.com/daddysboy21
Project-URL: Website, https://daddysboy21.link
Project-URL: Funding, https://buymeacoffee.com/PBEzMY14YC
Project-URL: Source, https://github.com/daddysboy21/africanjokes
Project-URL: Tracker, https://github.com/daddysboy21/africanjokes/issues
Project-URL: Documentation, https://github.com/daddysboy21/africanjokes/wiki
Project-URL: License, https://github.com/daddysboy21/africanjokes/blob/main/LICENSE
Keywords: jokes,africa,fun,humor,python
Classifier: Programming Language :: Python :: 3
Classifier: License :: OSI Approved :: MIT License
Classifier: Operating System :: OS Independent
Classifier: Intended Audience :: Developers
Classifier: Topic :: Games/Entertainment
Classifier: Topic :: Games/Entertainment
Requires-Python: >=3.8
License-File: LICENSE
Dynamic: author
Dynamic: home-page
Dynamic: license-file
Dynamic: requires-python
